googau/__init__.py
googau/calendar.py
googau/constants/__init__.py
googau/constants/drive_constants.py
googau/constants/sheets_constants.py
googau/documents.py
googau/drive.py
googau/gmail.py
googau/sessions.py
googau/sheets.py
googau-1.3.1.dist-info/LICENSE
googau-1.3.1.dist-info/METADATA
googau-1.3.1.dist-info/WHEEL
googau-1.3.1.dist-info/RECORD
